rom.v

module rom (
    input  [9:0] address,
    input  [9:0] i ,
    output reg [37:0] data
);

  reg [0:250] memory [37:0];

  initial begin
    // Here you can initialize the memory contents
    // Example initialization pattern:
    memory[0 ] =  400'b0000000000000000000000000000011000110000000000000000000000000000000000000000000000000000000000000000000000000000000000000000000000000000000000000000000000000000000000000000000000000000000000000000000000000000000000000000000000000000000000000000000000;
    memory[1 ] =  400'b0000000000000000000000000000011000110000000000000000000000000000000000000000000000000000000000000000000000000000000000000000000000000000000000000000000000000000000000000000000000000000000000000000000000000000000000000000000000000000000000000000000000;
    memory[2 ] =  400'b1111111111111111111111111111111111111111111111111111111111111111100000000000000000000000000000000000000000000000000000000000000000000000000000000000000000000000000000000000000000000000000000000000000000000000000000000000000000000000000000000000000000;
    memory[3 ] =  400'b0000000000000000000000000000011000110000000000000000000000000001100000000000000000000000000000000000000000000000000000000000000000000000000000000000000000000000000000000000000000000000000111110000000000000000000000000000000000000000000000000000000000;
    memory[4 ] =  400'b0000000000000000000000000000011000110000000000000000000000000001100000000000000000000000000000000011111111111111111111111111100000000111111111111111111111111000000000000000000000001111111111111111110000000000000000000000000011111111111000000000000000;
    memory[5 ] =  400'b0000000000000000000000000000011000110000000000000000000000000001100000000000000000000000000000000011111111111111111111111111100000000111111111111111111111111111000000000000000011111111111111111111111110000000000000000000000111111111111100000000000000;
    memory[6 ] =  400'b0000000000000000000000000000011000110000000000000000000000000001100000000000000000000000000000000011111111111111111111111111100000000111111111111111111111111111110000000000001111111111111111111111111111100000000000000000000111111111111110000000000000;
    memory[7 ] =  400'b0000000000111111111000000001111111111100000000000000000000000001100111111111100000000000000000000011111111000000000000000000000000000111111110000000000011111111110000000000011111111111000000000011111111110000000000000000001111111111111111000000000000;
    memory[8 ] =  400'b1111111111111111111000000001111111111100000000000000000000000001100111111111100000000000000000000011111111000000000000000000000000000111111110000000000000111111111000000001111111111000000000000000011111000000000000000000011111111011111111100000000000;
    memory[9 ] =  400'b0000000000111111111000000001111111111100000000000000000000000001111111111111111111111100000000000011111111000000000000000000000000000111111110000000000000011111111000000011111111110000000000000000000000000000000000000000111111111001111111100000000000;
    memory[10 ] = 400'b0000000000111111111000000001111111111100000000011000000000000000000111111111100000000000000000000011111111000000000000000000000000000111111110000000000000011111111000000011111111100000000000000000000000000000000000000001111111110000111111110000000000;
    memory[11 ] = 400'b1111111111111111111000000001111111111100000000011111100000000000000111111111100000000000000000000011111111111111111111111111000000000111111110000000000001111111111000000111111111000000000000000000000000000000000000000001111111100000011111111000000000;
    memory[12 ] = 400'b0000000000111111111111111111111111111100000000011111111110000000000000000000000000000000000000000011111111111111111111111111000000000111111111111111111111111111110000000111111111000000000111111111111111111000000000000011111111000000011111111100000000;
    memory[13 ] = 400'b1111111111111111111000000001111111111111111111111111111111000000000000000000000000000000000000000011111111111111111111111111000000000111111111111111111111111111100000000111111111000000000111111111111111111000000000000111111111000000001111111100000000;
    memory[14 ] = 400'b0000000000111111111000000001111111111110000000011111111111000000000111111111100000000000000000000011111111111111111111111111000000000111111111111111111111111110000000000111111111000000000111111111111111111000000000001111111110000000000111111110000000;
    memory[15 ] = 400'b0000000000111111111000000001111111111100000000011111111111111111111111111111111111111100000000000011111111000000000000000000000000000111111111111111111111000000000000000011111111100000000011111111011111111000000000011111111110000000000111111111000000;
    memory[16 ] = 400'b1111111111111111111000000001111111111100000000011111111111111111111111111111111111111100000000000011111111000000000000000000000000000111111110000000000000000000000000000011111111110000000000000000011111111000000000011111111111111111111111111111100000;
    memory[17 ] = 400'b0000000000111111111000000001111111111100000000011111111111000000000111111111100000000000000000000011111111000000000000000000000000000111111110000000000000000000000000000001111111111000000000000000011111111000000000111111111111111111111111111111110000;
    memory[18 ] = 400'b0000000000000000000000000001111111111100000000011111111111000000000000000000000000000000000000000011111111000000000000000000000000000111111110000000000000000000000000000000011111111111000000000011111111111000000001111111111111111111111111111111110000;
    memory[19 ] = 400'b0000000000000000000000000001111111111100000000011111111111000000000000000000000000000000000000000011111111000000000000000000000000000111111110000000000000000000000000000000001111111111111111111111111111111000000011111111110000000000000000111111111000;
    memory[20 ] = 400'b0000000000000000000000000001111111111100000000011111111111000000000000000000000000000000000000000011111111000000000000000000000000000111111110000000000000000000000000000000000011111111111111111111111111000000000111111111100000000000000000011111111100;
    memory[21 ] = 400'b0000000000111111111000000001111111111100000000011111111111000000000111111111100000000000000000000011111111000000000000000000000000000111111110000000000000000000000000000000000000011111111111111111111000000000000111111111000000000000000000001111111110;
    memory[22 ] = 400'b1111111111111111111000000001111111111100000000011111111111111111111111111111111111111110000000000000000000000000000000000000000000000000000000000000000000000000000000000000000000000000001111111000000000000000000000000000000000000000000000000000000000;
    memory[23 ] = 400'b0000000000111111111000000001111111111100000000011111111111111111111111111111111111111110000000000000000000000000000000000000000000000000000000000000000000000000000000000000000000000000000000000000000000000000000000000000000000000000000000000000000000;
    memory[24 ] = 400'b0000000000111111111000000001111111111100000000011111111111000000000111111111100000000000000000000000000000000000000000000000000000000000000000000000000000000000000000000000000000000000000000000000000000000000000000000000000000000000000000000000000000;
    memory[25 ] = 400'b1111111111111111111000000001111111111111111111111111111111000000000000000000000000000000000000000000011111111111111000011111100000000111110000011111111111111000011111111111111111100001111111111111110000001111111000000000111111100000001111111111111100;
    memory[26 ] = 400'b0000000000111111111111111111111111111100000000011111111110000000000000000000000000000000000000000001111111001111111000000111110000011111100000111111001111111000001111111111111111000001111111111111110000001111111100000001111111100000111111100111111100;
    memory[27 ] = 400'b1111111111111111111000000001111111111100000000011111100000000000000111111111100000000000000000000001111100000000000000000011111000111110000001111100000000000000000000001111000000000001111100000000000000001111111100000011111111100000111110000000000000;
    memory[28 ] = 400'b0000000000111111111000000001111111111100000000011000000000000000000111111111100000000000000000000001111111100000000000000001111101111100000000111111110000000000000000001111000000000001111100000000000000001111111110000111111111100000111111110000000000;
    memory[29 ] = 400'b0000000000111111111000000001111111111100000000000000000000000001111111111111111111111110000000000000111111111111100000000000111111111000000000011111111111110000000000001111000000000001111111111111110000001111001111001111101111100000011111111111110000;
    memory[30 ] = 400'b1111111111111111111000000001111111111100000000000000000000000001100111111111100000000000000000000000000011111111111000000000001111100000000000000011111111111100000000001111000000000001111111111111110000001111001111111111001111100000000001111111111100;
    memory[31 ] = 400'b0000000000111111111000000001111111111100000000000000000000000001100111111111100000000000000000000000000000000011111100000000001111100000000000000000000001111100000000001111000000000001111100000000000000001111000111111110001111100000000000000000111110;
    memory[32 ] = 400'b0000000000000000000000000000011000110000000000000000000000000001100000000000000000000000000000000000110000000001111100000000001111100000000000111000000001111100000000001111000000000001111100000000000000001111000011111100001111100000011000000000111110;
    memory[33 ] = 400'b0000000000000000000000000000011000110000000000000000000000000001100000000000000000000000000000000001111111111111111000000000001111100000000001111111111111111100000000001111000000000001111111111111110000001111000001111100001111100000111111111111111100;
    memory[34 ] = 400'b0000000000000000000000000000011000110000000000000000000000000001100000000000000000000000000000000000111111111111110000000000001111100000000000011111111111110000000000001111000000000001111111111111110000001111000000111000001111100000011111111111111000;
    memory[35 ] = 400'b0000000000000000000000000000011000110000000000000000000000000001100000000000000000000000000000000000000000000000000000000000000000000000000000000000000000000000000000000000000000000000000000000000000000000000000000000000000000000000000000000000000000;
    memory[36 ] = 400'b1111111111111111111111111111111111111111111111111111111111111111100000000000000000000000000000000000000000000000000000000000000000000000000000000000000000000000000000000000000000000000000000000000000000000000000000000000000000000000000000000000000000;
    memory[37 ] = 400'b0000000000000000000000000000011000110000000000000000000000000000000000000000000000000000000000000000000000000000000000000000000000000000000000000000000000000000000000000000000000000000000000000000000000000000000000000000000000000000000000000000000000;

  end
  reg tmp;
  always @(i) begin

    data [	37	]=	    memory[	0	]	[i];
    data [	36	]=	    memory[	1	]	[i];
    data [	35	]=	    memory[	2	]	[i];
    data [	34	]=	    memory[	3	]	[i];
    data [	33	]=	    memory[	4	]	[i];
    data [	32	]=	    memory[	5	]	[i];
    data [	31	]=	    memory[	6	]	[i];
    data [	30	]=	    memory[	7	]	[i];
    data [	29	]=	    memory[	8	]	[i];
    data [	28	]=	    memory[	9	]	[i];
    data [	27	]=	    memory[	10	]	[i];
    data [	26	]=	    memory[	11	]	[i];
    data [	25	]=	    memory[	12	]	[i];
    data [	24	]=	    memory[	13	]	[i];
    data [	23	]=	    memory[	14	]	[i];
    data [	22	]=	    memory[	15	]	[i];
    data [	21	]=	    memory[	16	]	[i];
    data [	20	]=	    memory[	17	]	[i];
    data [	19	]=	    memory[	18	]	[i];
    data [	18	]=	    memory[	19	]	[i];
    data [	17	]=	    memory[	20	]	[i];
    data [	16	]=	    memory[	21	]	[i];
    data [	15	]=	    memory[	22	]	[i];
    data [	14	]=	    memory[	23	]	[i];
    data [	13	]=	    memory[	24	]	[i];
    data [	12	]=		memory[	25	]	[i];
    data [	11	]=		memory[	26	]	[i];
    data [	10	]=		memory[	27	]	[i];
    data [	9	]=		memory[	28	]	[i];
    data [	8	]=		memory[	29	]	[i];
    data [	7	]=		memory[	30	]	[i];
    data [	6	]=		memory[	31	]	[i];
    data [	5	]=		memory[	32	]	[i];
    data [	4	]=		memory[	33	]	[i];
    data [	3	]=		memory[	34	]	[i];
    data [	2	]=		memory[	35	]	[i];
    data [	1	]=		memory[	36	]	[i];
    data [	0	]=		memory[	37	]	[i];
 
  end

endmodule

tb.v
// Code your testbench here
// or browse Examples
module rom_testbench;

    reg [9:0] address;
    wire [37:0] data;
    reg [9:0] i;
    
    // Instantiate the ROM module
    rom rom_inst (
        .address(address),
        .i(i),
        .data(data)
    );

    // Clock generation
    reg clk = 0;
    always begin
    #5 clk = ~clk;
    end
    integer j;
    
    // Stimulus generation
    initial begin
    $dumpfile("dump.vcd");
    $dumpvars;
    i = 0;
    // Initialize address
    for (j = 0; j <=250; j = j + 1) begin
        #1;  
        i = i + 1;
        
    end
    
    $finish;
    end

// Monitor


endmodule

dump.vcd
$date
Fri Aug 18 03:10:07 2023
$end
$version
Riviera-PRO Version 2022.04.117.8517
$end
$timescale
1 ns
$end

$scope module rom_testbench $end
$var wire 38 ! data [37:0] $end
$var reg 10 " address [9:0] $end
$var reg 10 # i [9:0] $end
$var reg 1 $ clk $end
$var integer 32 % j $end

$scope module rom_inst $end
$var wire 10 & address [9:0] $end
$var wire 10 ' i [9:0] $end
$var reg 38 ( data [37:0] $end
$var reg 1 ) tmp $end
$upscope $end

$upscope $end

$enddefinitions $end
$dumpvars
b0 !
bx "
b0 #
0$
b0 %
bx &
b0 '
b0 (
x)
$end
#1
b1 #
b1 %
b1 '
b100000100101001000001001010010000010 (
b100000100101001000001001010010000010 !
#2
b10 #
b10 %
b10 '
#3
b11 #
b11 %
b11 '
#4
b100 #
b100 %
b100 '
#5
1$
b101 #
b101 %
b101 '
#6
b110 #
b110 %
b110 '
#7
b111 #
b111 %
b111 '
#8
b1000 #
b1000 %
b1000 '
#9
b1001 #
b1001 %
b1001 '
#10
0$
b1010 #
b1010 %
b1010 '
#11
b1011 #
b1011 %
b1011 '
b100001111111111100011111111111000010 (
b100001111111111100011111111111000010 !
#12
b1100 #
b1100 %
b1100 '
#13
b1101 #
b1101 %
b1101 '
#14
b1110 #
b1110 %
b1110 '
#15
1$
b1111 #
b1111 %
b1111 '
#16
b10000 #
b10000 %
b10000 '
#17
b10001 #
b10001 %
b10001 '
#18
b10010 #
b10010 %
b10010 '
#19
b10011 #
b10011 %
b10011 '
#20
0$
b10100 #
b10100 %
b10100 '
b100000000010000000000000100000000010 (
b100000000010000000000000100000000010 !
#21
b10101 #
b10101 %
b10101 '
#22
b10110 #
b10110 %
b10110 '
#23
b10111 #
b10111 %
b10111 '
#24
b11000 #
b11000 %
b11000 '
#25
1$
b11001 #
b11001 %
b11001 '
#26
b11010 #
b11010 %
b11010 '
#27
b11011 #
b11011 %
b11011 '
#28
b11100 #
b11100 %
b11100 '
b100001111111111111111111111111000010 (
b100001111111111111111111111111000010 !
#29
b11101 #
b11101 %
b11101 '
#30
0$
b11110 #
b11110 %
b11110 '
b11111111111111111111111111111111111111 (
b11111111111111111111111111111111111111 !
#31
b11111 #
b11111 %
b11111 '
#32
b100000 #
b100000 %
b100000 '
b100001111111111111111111111111000010 (
b100001111111111111111111111111000010 !
#33
b100001 #
b100001 %
b100001 '
#34
b100010 #
b100010 %
b100010 '
#35
1$
b100011 #
b100011 %
b100011 '
b11111111111111111111111111111111111111 (
b11111111111111111111111111111111111111 !
#36
b100100 #
b100100 %
b100100 '
#37
b100101 #
b100101 %
b100101 '
b100001111111111111111111111111000010 (
b100001111111111111111111111111000010 !
#38
b100110 #
b100110 %
b100110 '
#39
b100111 #
b100111 %
b100111 '
b100000000001100000000001000000000010 (
b100000000001100000000001000000000010 !
#40
0$
b101000 #
b101000 %
b101000 '
b100000000001000000000001000000000010 (
b100000000001000000000001000000000010 !
#41
b101001 #
b101001 %
b101001 '
#42
b101010 #
b101010 %
b101010 '
#43
b101011 #
b101011 %
b101011 '
#44
b101100 #
b101100 %
b101100 '
#45
1$
b101101 #
b101101 %
b101101 '
#46
b101110 #
b101110 %
b101110 '
#47
b101111 #
b101111 %
b101111 '
#48
b110000 #
b110000 %
b110000 '
b100000001111111111111111111000000010 (
b100000001111111111111111111000000010 !
#49
b110001 #
b110001 %
b110001 '
#50
0$
b110010 #
b110010 %
b110010 '
b100000000111111111111111110000000010 (
b100000000111111111111111110000000010 !
#51
b110011 #
b110011 %
b110011 '
#52
b110100 #
b110100 %
b110100 '
#53
b110101 #
b110101 %
b110101 '
#54
b110110 #
b110110 %
b110110 '
b100000000011111111111111100000000010 (
b100000000011111111111111100000000010 !
#55
1$
b110111 #
b110111 %
b110111 '
#56
b111000 #
b111000 %
b111000 '
#57
b111001 #
b111001 %
b111001 '
#58
b111010 #
b111010 %
b111010 '
b100000000001111111111111000000000010 (
b100000000001111111111111000000000010 !
#59
b111011 #
b111011 %
b111011 '
b100000000000011000001100000000000010 (
b100000000000011000001100000000000010 !
#60
0$
b111100 #
b111100 %
b111100 '
#61
b111101 #
b111101 %
b111101 '
#62
b111110 #
b111110 %
b111110 '
#63
b111111 #
b111111 %
b111111 '
#64
b1000000 #
b1000000 %
b1000000 '
b111111110000011000001100000111111110 (
b111111110000011000001100000111111110 !
#65
1$
b1000001 #
b1000001 %
b1000001 '
#66
b1000010 #
b1000010 %
b1000010 '
b10000011000001100000100000000 (
b10000011000001100000100000000 !
#67
b1000011 #
b1000011 %
b1000011 '
#68
b1000100 #
b1000100 %
b1000100 '
b1111100111100011110011111000000 (
b1111100111100011110011111000000 !
#69
b1000101 #
b1000101 %
b1000101 '
#70
0$
b1000110 #
b1000110 %
b1000110 '
#71
b1000111 #
b1000111 %
b1000111 '
#72
b1001000 #
b1001000 %
b1001000 '
#73
b1001001 #
b1001001 %
b1001001 '
#74
b1001010 #
b1001010 %
b1001010 '
#75
1$
b1001011 #
b1001011 %
b1001011 '
#76
b1001100 #
b1001100 %
b1001100 '
#77
b1001101 #
b1001101 %
b1001101 '
#78
b1001110 #
b1001110 %
b1001110 '
b10000011000001100000100000000 (
b10000011000001100000100000000 !
#79
b1001111 #
b1001111 %
b1001111 '
#80
0$
b1010000 #
b1010000 %
b1010000 '
#81
b1010001 #
b1010001 %
b1010001 '
#82
b1010010 #
b1010010 %
b1010010 '
#83
b1010011 #
b1010011 %
b1010011 '
#84
b1010100 #
b1010100 %
b1010100 '
#85
1$
b1010101 #
b1010101 %
b1010101 '
#86
b1010110 #
b1010110 %
b1010110 '
#87
b1010111 #
b1010111 %
b1010111 '
b1100000100000000 (
b1100000100000000 !
#88
b1011000 #
b1011000 %
b1011000 '
b0 (
b0 !
#89
b1011001 #
b1011001 %
b1011001 '
#90
0$
b1011010 #
b1011010 %
b1011010 '
#91
b1011011 #
b1011011 %
b1011011 '
#92
b1011100 #
b1011100 %
b1011100 '
#93
b1011101 #
b1011101 %
b1011101 '
#94
b1011110 #
b1011110 %
b1011110 '
#95
1$
b1011111 #
b1011111 %
b1011111 '
#96
b1100000 #
b1100000 %
b1100000 '
#97
b1100001 #
b1100001 %
b1100001 '
#98
b1100010 #
b1100010 %
b1100010 '
#99
b1100011 #
b1100011 %
b1100011 '
b1111111111111111110000000000000000 (
b1111111111111111110000000000000000 !
#100
0$
b1100100 #
b1100100 %
b1100100 '
b1111111111111111110000111000010000 (
b1111111111111111110000111000010000 !
#101
b1100101 #
b1100101 %
b1100101 '
b1111111111111111110000111100111000 (
b1111111111111111110000111100111000 !
#102
b1100110 #
b1100110 %
b1100110 '
b1111111111111111110001111100111000 (
b1111111111111111110001111100111000 !
#103
b1100111 #
b1100111 %
b1100111 '
b1111111111111111110001111100011000 (
b1111111111111111110001111100011000 !
#104
b1101000 #
b1101000 %
b1101000 '
#105
1$
b1101001 #
b1101001 %
b1101001 '
b1111111111111111110001101110011000 (
b1111111111111111110001101110011000 !
#106
b1101010 #
b1101010 %
b1101010 '
#107
b1101011 #
b1101011 %
b1101011 '
b1110000111100000000001001110011000 (
b1110000111100000000001001110011000 !
#108
b1101100 #
b1101100 %
b1101100 '
b1110000111100000000001000110011000 (
b1110000111100000000001000110011000 !
#109
b1101101 #
b1101101 %
b1101101 '
b1110000111100000000001100110011000 (
b1110000111100000000001100110011000 !
#110
0$
b1101110 #
b1101110 %
b1101110 '
#111
b1101111 #
b1101111 %
b1101111 '
b1110000111100000000001100111011000 (
b1110000111100000000001100111011000 !
#112
b1110000 #
b1110000 %
b1110000 '
b1110000111100000000001100111111000 (
b1110000111100000000001100111111000 !
#113
b1110001 #
b1110001 %
b1110001 '
#114
b1110010 #
b1110010 %
b1110010 '
b1110000111100000000001100011111000 (
b1110000111100000000001100011111000 !
#115
1$
b1110011 #
b1110011 %
b1110011 '
b1110000111100000000001100011110000 (
b1110000111100000000001100011110000 !
#116
b1110100 #
b1110100 %
b1110100 '
b1110000111100000000000000001100000 (
b1110000111100000000000000001100000 !
#117
b1110101 #
b1110101 %
b1110101 '
b1110000111100000000000000000000000 (
b1110000111100000000000000000000000 !
#118
b1110110 #
b1110110 %
b1110110 '
#119
b1110111 #
b1110111 %
b1110111 '
#120
0$
b1111000 #
b1111000 %
b1111000 '
b1110000111100000000001000000000000 (
b1110000111100000000001000000000000 !
#121
b1111001 #
b1111001 %
b1111001 '
#122
b1111010 #
b1111010 %
b1111010 '
b1110000111100000000001100000000000 (
b1110000111100000000001100000000000 !
#123
b1111011 #
b1111011 %
b1111011 '
b1110000111100000000001110000000000 (
b1110000111100000000001110000000000 !
#124
b1111100 #
b1111100 %
b1111100 '
b1110000111100000000001111000000000 (
b1110000111100000000001111000000000 !
#125
1$
b1111101 #
b1111101 %
b1111101 '
b1110000000000000000001111100000000 (
b1110000000000000000001111100000000 !
#126
b1111110 #
b1111110 %
b1111110 '
b111100000000 (
b111100000000 !
#127
b1111111 #
b1111111 %
b1111111 '
b11111111000 (
b11111111000 !
#128
b10000000 #
b10000000 %
b10000000 '
b1111111000 (
b1111111000 !
#129
b10000001 #
b10000001 %
b10000001 '
b111111000 (
b111111000 !
#130
0$
b10000010 #
b10000010 %
b10000010 '
b1111111000 (
b1111111000 !
#131
b10000011 #
b10000011 %
b10000011 '
b11111111000 (
b11111111000 !
#132
b10000100 #
b10000100 %
b10000100 '
b111100000000 (
b111100000000 !
#133
b10000101 #
b10000101 %
b10000101 '
#134
b10000110 #
b10000110 %
b10000110 '
b1111111111111111110001111000000000 (
b1111111111111111110001111000000000 !
#135
1$
b10000111 #
b10000111 %
b10000111 '
b1111111111111111110001110000000000 (
b1111111111111111110001110000000000 !
#136
b10001000 #
b10001000 %
b10001000 '
b1111111111111111110001100000000000 (
b1111111111111111110001100000000000 !
#137
b10001001 #
b10001001 %
b10001001 '
#138
b10001010 #
b10001010 %
b10001010 '
b1111111111111111110001000000000000 (
b1111111111111111110001000000000000 !
#139
b10001011 #
b10001011 %
b10001011 '
b1111111111111111110000000000000000 (
b1111111111111111110000000000000000 !
#140
0$
b10001100 #
b10001100 %
b10001100 '
#141
b10001101 #
b10001101 %
b10001101 '
#142
b10001110 #
b10001110 %
b10001110 '
b1110000011110000000000010000010000 (
b1110000011110000000000010000010000 !
#143
b10001111 #
b10001111 %
b10001111 '
b1110000011110000000000111000110000 (
b1110000011110000000000111000110000 !
#144
b10010000 #
b10010000 %
b10010000 '
b1110000011110000000001111100111000 (
b1110000011110000000001111100111000 !
#145
1$
b10010001 #
b10010001 %
b10010001 '
#146
b10010010 #
b10010010 %
b10010010 '
b1110000011110000000001111100011000 (
b1110000011110000000001111100011000 !
#147
b10010011 #
b10010011 %
b10010011 '
b1110000011110000000001101110011000 (
b1110000011110000000001101110011000 !
#148
b10010100 #
b10010100 %
b10010100 '
#149
b10010101 #
b10010101 %
b10010101 '
b1110000011110000000001001110011000 (
b1110000011110000000001001110011000 !
#150
0$
b10010110 #
b10010110 %
b10010110 '
#151
b10010111 #
b10010111 %
b10010111 '
b1110000011110000000001100110011000 (
b1110000011110000000001100110011000 !
#152
b10011000 #
b10011000 %
b10011000 '
#153
b10011001 #
b10011001 %
b10011001 '
b1111000011110000000001100110011000 (
b1111000011110000000001100110011000 !
#154
b10011010 #
b10011010 %
b10011010 '
b1111000111110000000001100111111000 (
b1111000111110000000001100111111000 !
#155
1$
b10011011 #
b10011011 %
b10011011 '
b1111100111100000000001100111111000 (
b1111100111100000000001100111111000 !
#156
b10011100 #
b10011100 %
b10011100 '
b1111111111100000000001100111111000 (
b1111111111100000000001100111111000 !
#157
b10011101 #
b10011101 %
b10011101 '
b1111111111100000000001100011110000 (
b1111111111100000000001100011110000 !
#158
b10011110 #
b10011110 %
b10011110 '
b111111111100000000000000011110000 (
b111111111100000000000000011110000 !
#159
b10011111 #
b10011111 %
b10011111 '
b111111111100000000000000000000000 (
b111111111100000000000000000000000 !
#160
0$
b10100000 #
b10100000 %
b10100000 '
b111111111000000000000000000000000 (
b111111111000000000000000000000000 !
#161
b10100001 #
b10100001 %
b10100001 '
b11111111000000000000000000000000 (
b11111111000000000000000000000000 !
#162
b10100010 #
b10100010 %
b10100010 '
b11111110000000000001000000000000 (
b11111110000000000001000000000000 !
#163
b10100011 #
b10100011 %
b10100011 '
b111100000000000001100000000000 (
b111100000000000001100000000000 !
#164
b10100100 #
b10100100 %
b10100100 '
b1100000000000 (
b1100000000000 !
#165
1$
b10100101 #
b10100101 %
b10100101 '
#166
b10100110 #
b10100110 %
b10100110 '
#167
b10100111 #
b10100111 %
b10100111 '
#168
b10101000 #
b10101000 %
b10101000 '
#169
b10101001 #
b10101001 %
b10101001 '
b1111111111000 (
b1111111111000 !
#170
0$
b10101010 #
b10101010 %
b10101010 '
b111100000000001111111111000 (
b111100000000001111111111000 !
#171
b10101011 #
b10101011 %
b10101011 '
b11111111000000001111111111000 (
b11111111000000001111111111000 !
#172
b10101100 #
b10101100 %
b10101100 '
b111111111100000001111111111000 (
b111111111100000001111111111000 !
#173
b10101101 #
b10101101 %
b10101101 '
b111111111100000001100000000000 (
b111111111100000001100000000000 !
#174
b10101110 #
b10101110 %
b10101110 '
b1111111111110000001100000000000 (
b1111111111110000001100000000000 !
#175
1$
b10101111 #
b10101111 %
b10101111 '
b11111111111111000001100000000000 (
b11111111111111000001100000000000 !
#176
b10110000 #
b10110000 %
b10110000 '
#177
b10110001 #
b10110001 %
b10110001 '
b111111111111111100001100000000000 (
b111111111111111100001100000000000 !
#178
b10110010 #
b10110010 %
b10110010 '
#179
b10110011 #
b10110011 %
b10110011 '
b111111000011111100001000000000000 (
b111111000011111100001000000000000 !
#180
0$
b10110100 #
b10110100 %
b10110100 '
b111110000001111110000000000000000 (
b111110000001111110000000000000000 !
#181
b10110101 #
b10110101 %
b10110101 '
b1111100000000111110000000000000000 (
b1111100000000111110000000000000000 !
#182
b10110110 #
b10110110 %
b10110110 '
b1111000000000011110000000000000000 (
b1111000000000011110000000000000000 !
#183
b10110111 #
b10110111 %
b10110111 '
#184
b10111000 #
b10111000 %
b10111000 '
b1111000000000011110001111111111000 (
b1111000000000011110001111111111000 !
#185
1$
b10111001 #
b10111001 %
b10111001 '
b1110000000000001110001111111111000 (
b1110000000000001110001111111111000 !
#186
b10111010 #
b10111010 %
b10111010 '
#187
b10111011 #
b10111011 %
b10111011 '
b1110000000000001111001111111111000 (
b1110000000000001111001111111111000 !
#188
b10111100 #
b10111100 %
b10111100 '
b11110000011100001111001111111111000 (
b11110000011100001111001111111111000 !
#189
b10111101 #
b10111101 %
b10111101 '
b11110000011110001111001100110011000 (
b11110000011110001111001100110011000 !
#190
0$
b10111110 #
b10111110 %
b10111110 '
#191
b10111111 #
b10111111 %
b10111111 '
#192
b11000000 #
b11000000 %
b11000000 '
#193
b11000001 #
b11000001 %
b11000001 '
b1110000011110001111001100110011000 (
b1110000011110001111001100110011000 !
#194
b11000010 #
b11000010 %
b11000010 '
b1110000011110001110001100110011000 (
b1110000011110001110001100110011000 !
#195
1$
b11000011 #
b11000011 %
b11000011 '
b1111000011110011110001100110011000 (
b1111000011110011110001100110011000 !
#196
b11000100 #
b11000100 %
b11000100 '
#197
b11000101 #
b11000101 %
b11000101 '
b1111000011100011110001100110011000 (
b1111000011100011110001100110011000 !
#198
b11000110 #
b11000110 %
b11000110 '
b1111100011111111110001100110011000 (
b1111100011111111110001100110011000 !
#199
b11000111 #
b11000111 %
b11000111 '
b111100011111111110000000000000000 (
b111100011111111110000000000000000 !
#200
0$
b11001000 #
b11001000 %
b11001000 '
b111100011111111100000000000000000 (
b111100011111111100000000000000000 !
#201
b11001001 #
b11001001 %
b11001001 '
#202
b11001010 #
b11001010 %
b11001010 '
b11100011111111100000000000000000 (
b11100011111111100000000000000000 !
#203
b11001011 #
b11001011 %
b11001011 '
b11000011111111000000000000000000 (
b11000011111111000000000000000000 !
#204
b11001100 #
b11001100 %
b11001100 '
b1000011111111000000000000000000 (
b1000011111111000000000000000000 !
#205
1$
b11001101 #
b11001101 %
b11001101 '
b11111111000001111111111000 (
b11111111000001111111111000 !
#206
b11001110 #
b11001110 %
b11001110 '
b1111111111000 (
b1111111111000 !
#207
b11001111 #
b11001111 %
b11001111 '
#208
b11010000 #
b11010000 %
b11010000 '
#209
b11010001 #
b11010001 %
b11010001 '
b1111000000000 (
b1111000000000 !
#210
0$
b11010010 #
b11010010 %
b11010010 '
#211
b11010011 #
b11010011 %
b11010011 '
b1111110000000 (
b1111110000000 !
#212
b11010100 #
b11010100 %
b11010100 '
b110000111111000000 (
b110000111111000000 !
#213
b11010101 #
b11010101 %
b11010101 '
b1110000001111100000 (
b1110000001111100000 !
#214
b11010110 #
b11010110 %
b11010110 '
b11110000000111110000 (
b11110000000111110000 !
#215
1$
b11010111 #
b11010111 %
b11010111 '
b111110000000011111000 (
b111110000000011111000 !
#216
b11011000 #
b11011000 %
b11011000 '
b11111110000000011111000 (
b11111110000000011111000 !
#217
b11011001 #
b11011001 %
b11011001 '
b111111110000000111111000 (
b111111110000000111111000 !
#218
b11011010 #
b11011010 %
b11011010 '
b1111111110000001111110000 (
b1111111110000001111110000 !
#219
b11011011 #
b11011011 %
b11011011 '
b11111111110000011111000000 (
b11111111110000011111000000 !
#220
0$
b11011100 #
b11011100 %
b11011100 '
b1111111111110000111110000000 (
b1111111111110000111110000000 !
#221
b11011101 #
b11011101 %
b11011101 '
b11111111111100001111100000000 (
b11111111111100001111100000000 !
#222
b11011110 #
b11011110 %
b11011110 '
b111111111111000001111000000000 (
b111111111111000001111000000000 !
#223
b11011111 #
b11011111 %
b11011111 '
b1111111111110000001111111111000 (
b1111111111110000001111111111000 !
#224
b11100000 #
b11100000 %
b11100000 '
b111111111111110000001111111111000 (
b111111111111110000001111111111000 !
#225
1$
b11100001 #
b11100001 %
b11100001 '
b1111111111111110000001111111111000 (
b1111111111111110000001111111111000 !
#226
b11100010 #
b11100010 %
b11100010 '
b1111111111001110000001111111111000 (
b1111111111001110000001111111111000 !
#227
b11100011 #
b11100011 %
b11100011 '
b1111111100001110000001111111111000 (
b1111111100001110000001111111111000 !
#228
b11100100 #
b11100100 %
b11100100 '
b1111111000001110000000000000000000 (
b1111111000001110000000000000000000 !
#229
b11100101 #
b11100101 %
b11100101 '
b1111110000001110000000000000000000 (
b1111110000001110000000000000000000 !
#230
0$
b11100110 #
b11100110 %
b11100110 '
b1111000000001110000000000000000000 (
b1111000000001110000000000000000000 !
#231
b11100111 #
b11100111 %
b11100111 '
b1111100000001110000000000000000000 (
b1111100000001110000000000000000000 !
#232
b11101000 #
b11101000 %
b11101000 '
b1111110000001110000000000000000000 (
b1111110000001110000000000000000000 !
#233
b11101001 #
b11101001 %
b11101001 '
b1111111000001110000000111000010000 (
b1111111000001110000000111000010000 !
#234
b11101010 #
b11101010 %
b11101010 '
b1111111110001110000000111100111000 (
b1111111110001110000000111100111000 !
#235
1$
b11101011 #
b11101011 %
b11101011 '
b1111111111001110000001111100111000 (
b1111111111001110000001111100111000 !
#236
b11101100 #
b11101100 %
b11101100 '
b111111111111110000001111100011000 (
b111111111111110000001111100011000 !
#237
b11101101 #
b11101101 %
b11101101 '
b11111111111110000001111100011000 (
b11111111111110000001111100011000 !
#238
b11101110 #
b11101110 %
b11101110 '
b1111111111110000001101110011000 (
b1111111111110000001101110011000 !
#239
b11101111 #
b11101111 %
b11101111 '
b111111111111000001101110011000 (
b111111111111000001101110011000 !
#240
0$
b11110000 #
b11110000 %
b11110000 '
b1111111111100001001110011000 (
b1111111111100001001110011000 !
#241
b11110001 #
b11110001 %
b11110001 '
b111111111110001000110011000 (
b111111111110001000110011000 !
#242
b11110010 #
b11110010 %
b11110010 '
b11111111110001100110011000 (
b11111111110001100110011000 !
#243
b11110011 #
b11110011 %
b11110011 '
b111111110001100110011000 (
b111111110001100110011000 !
